pdf_lightner/.jukit/.jukit_info.json
pdf_lightner/__init__.py
pdf_lightner/main.py
pdf_lightner-0.1.0.dist-info/LICENSE
pdf_lightner-0.1.0.dist-info/METADATA
pdf_lightner-0.1.0.dist-info/WHEEL
pdf_lightner-0.1.0.dist-info/entry_points.txt
pdf_lightner-0.1.0.dist-info/RECORD
